template_maker/__init__.py
template_maker/main.py
template_maker/configuration/conan_application.json
template_maker/configuration/conan_library.json
template_maker/configuration/template/.clang-format
template_maker/configuration/template/.gitignore
template_maker/configuration/template/LICENSE
template_maker/configuration/template/README.md
template_maker/configuration/template/app/CMakeLists.txt
template_maker/configuration/template/app/conanfile.txt
template_maker/configuration/template/app/main.cpp
template_maker/configuration/template/lib/CMakeLists.txt
template_maker/configuration/template/lib/app/CMakeLists.txt
template_maker/configuration/template/lib/app/main.cpp
template_maker/configuration/template/lib/lib/CMakeLists.txt
template_maker/configuration/template/lib/lib/conanfile.py
template_maker/configuration/template/lib/lib/include/main.h
template_maker/configuration/template/lib/lib/src/main.cpp
template_maker/configuration/template/lib/test/CMakeLists.txt
template_maker/configuration/template/lib/test/conanfile.txt
template_maker/configuration/template/lib/test/src/main.cpp
template_maker-0.0.1.dist-info/entry_points.txt
template_maker-0.0.1.dist-info/LICENSE
template_maker-0.0.1.dist-info/WHEEL
template_maker-0.0.1.dist-info/METADATA
template_maker-0.0.1.dist-info/RECORD
