Metadata-Version: 2.1
Name: template_maker
Version: 0.0.1
Summary: with the help of this script, create CMake supported conan template empty structure.
Home-page: https://github.com/shajeen/template-maker
Author: Sheik S Shajeen Ahamed
Author-email: shajeenahmed@gmail.com
Classifier: License :: OSI Approved :: GNU General Public License v3 or later (GPLv3+)
